odoo8_addon_base_suspend_security-8.0.1.0.1-py2.7-nspkg.pth
odoo8_addon_base_suspend_security-8.0.1.0.1.dist-info/DESCRIPTION.rst
odoo8_addon_base_suspend_security-8.0.1.0.1.dist-info/METADATA
odoo8_addon_base_suspend_security-8.0.1.0.1.dist-info/RECORD
odoo8_addon_base_suspend_security-8.0.1.0.1.dist-info/WHEEL
odoo8_addon_base_suspend_security-8.0.1.0.1.dist-info/metadata.json
odoo8_addon_base_suspend_security-8.0.1.0.1.dist-info/namespace_packages.txt
odoo8_addon_base_suspend_security-8.0.1.0.1.dist-info/top_level.txt
odoo_addons/base_suspend_security/README.rst
odoo_addons/base_suspend_security/__init__.py
odoo_addons/base_suspend_security/__openerp__.py
odoo_addons/base_suspend_security/base_suspend_security.py
odoo_addons/base_suspend_security/i18n/ar.po
odoo_addons/base_suspend_security/i18n/ca.po
odoo_addons/base_suspend_security/i18n/da.po
odoo_addons/base_suspend_security/i18n/de.po
odoo_addons/base_suspend_security/i18n/el_GR.po
odoo_addons/base_suspend_security/i18n/es.po
odoo_addons/base_suspend_security/i18n/es_ES.po
odoo_addons/base_suspend_security/i18n/fi.po
odoo_addons/base_suspend_security/i18n/fr.po
odoo_addons/base_suspend_security/i18n/fr_CH.po
odoo_addons/base_suspend_security/i18n/hr.po
odoo_addons/base_suspend_security/i18n/hr_HR.po
odoo_addons/base_suspend_security/i18n/it.po
odoo_addons/base_suspend_security/i18n/nl.po
odoo_addons/base_suspend_security/i18n/pt_BR.po
odoo_addons/base_suspend_security/i18n/sl.po
odoo_addons/base_suspend_security/i18n/tr.po
odoo_addons/base_suspend_security/i18n/tr_TR.po
odoo_addons/base_suspend_security/i18n/zh_CN.po
odoo_addons/base_suspend_security/models/__init__.py
odoo_addons/base_suspend_security/models/ir_model_access.py
odoo_addons/base_suspend_security/models/ir_rule.py
odoo_addons/base_suspend_security/models/res_users.py
odoo_addons/base_suspend_security/static/description/icon.png
odoo_addons/base_suspend_security/tests/__init__.py
odoo_addons/base_suspend_security/tests/test_base_suspend_security.py
